{
  "id": "Q39427",
  "name": "Surrealism",
  "description": "A cultural movement that developed in Europe in the 1920s, known for unexpected juxtapositions.",
  "wikidataId": "Q39427",
  "cosmosPosition": { "x": 0, "y": 8, "z": 0 },
  "galleryModelPath": "",
  "artists": [
    {
      "id": "Q5577",
      "name": "Salvador Dalí",
      "birthYear": "1904",
      "deathYear": "1989",
      "portraitUrl": "https://upload.wikimedia.org/wikipedia/commons/1/14/Salvador_Dal%C3%AD_1939.jpg",
      "portraitThumbnailUrl": "https://upload.wikimedia.org/wikipedia/commons/1/14/Salvador_Dal%C3%AD_1939.jpg",
      "localPosition": { "x": 0.5, "y": 0.4, "z": 0.3 },
      "artworks": [
        {
          "id": "Q154015",
          "title": "The Persistence of Memory",
          "year": "1931",
          "imageHighResUrl": "https://upload.wikimedia.org/wikipedia/en/d/dd/The_Persistence_of_Memory.jpg",
          "imageThumbnailUrl": "https://upload.wikimedia.org/wikipedia/en/d/dd/The_Persistence_of_Memory.jpg",
          "dimensions": { "width": 3000, "height": 2180 },
          "aspectRatio": 1.38,
          "description": "Iconic surrealist painting featuring melting clocks in a desert landscape."
        }
      ]
    },
    {
      "id": "Q42048",
      "name": "René Magritte",
      "birthYear": "1898",
      "deathYear": "1967",
      "portraitUrl": "https://upload.wikimedia.org/wikipedia/commons/7/79/Ren%C3%A9_Magritte.jpg",
      "portraitThumbnailUrl": "https://upload.wikimedia.org/wikipedia/commons/7/79/Ren%C3%A9_Magritte.jpg",
      "localPosition": { "x": -0.6, "y": 0.3, "z": 0.5 },
      "artworks": [
        {
          "id": "Q33438",
          "title": "The Son of Man",
          "year": "1964",
          "imageHighResUrl": "https://upload.wikimedia.org/wikipedia/en/e/e5/Magritte_TheSonOfMan.jpg",
          "imageThumbnailUrl": "https://upload.wikimedia.org/wikipedia/en/e/e5/Magritte_TheSonOfMan.jpg",
          "dimensions": { "width": 3000, "height": 3860 },
          "aspectRatio": 0.78,
          "description": "Self-portrait of a man in an overcoat with a green apple obscuring his face."
        },
        {
          "id": "Q3345",
          "title": "The Treachery of Images",
          "year": "1929",
          "imageHighResUrl": "https://upload.wikimedia.org/wikipedia/en/b/b9/MagrittePipe.jpg",
          "imageThumbnailUrl": "https://upload.wikimedia.org/wikipedia/en/b/b9/MagrittePipe.jpg",
          "dimensions": { "width": 3000, "height": 2200 },
          "aspectRatio": 1.36,
          "description": "Painting of a pipe with a famous philosophical caption."
        }
      ]
    },
    {
      "id": "Q151558",
      "name": "Joan Miró",
      "birthYear": "1893",
      "deathYear": "1983",
      "portraitUrl": "https://upload.wikimedia.org/wikipedia/commons/6/6c/Portrait_of_Joan_Mir%C3%B3%2C_Barcelona_1935_June_13.jpg",
      "portraitThumbnailUrl": "https://upload.wikimedia.org/wikipedia/commons/6/6c/Portrait_of_Joan_Mir%C3%B3%2C_Barcelona_1935_June_13.jpg",
      "localPosition": { "x": 0.2, "y": -0.5, "z": 0.6 },
      "artworks": [
        {
          "id": "Q12345",
          "title": "The Harlequin's Carnival",
          "year": "1925",
          "imageHighResUrl": "https://upload.wikimedia.org/wikipedia/en/0/0b/Joan_Miro_-_Carnaval_d%27Arlequin.jpg",
          "imageThumbnailUrl": "https://upload.wikimedia.org/wikipedia/en/0/0b/Joan_Miro_-_Carnaval_d%27Arlequin.jpg",
          "dimensions": { "width": 3000, "height": 2300 },
          "aspectRatio": 1.30,
          "description": "One of the artist's best-known surrealist works with biomorphic forms."
        }
      ]
    },
    {
      "id": "Q165709",
      "name": "Max Ernst",
      "birthYear": "1891",
      "deathYear": "1976",
      "portraitUrl": "https://upload.wikimedia.org/wikipedia/commons/8/8e/Max_Ernst_1968.jpg",
      "portraitThumbnailUrl": "https://upload.wikimedia.org/wikipedia/commons/8/8e/Max_Ernst_1968.jpg",
      "localPosition": { "x": -0.4, "y": -0.3, "z": -0.4 },
      "artworks": [
        {
          "id": "Q23456",
          "title": "The Elephant Celebes",
          "year": "1921",
          "imageHighResUrl": "https://upload.wikimedia.org/wikipedia/en/4/4e/The_Elephant_Celebes.jpg",
          "imageThumbnailUrl": "https://upload.wikimedia.org/wikipedia/en/4/4e/The_Elephant_Celebes.jpg",
          "dimensions": { "width": 3000, "height": 2400 },
          "aspectRatio": 1.25,
          "description": "Early surrealist masterpiece combining mechanical and organic forms."
        }
      ]
    },
    {
      "id": "Q160271",
      "name": "Yves Tanguy",
      "birthYear": "1900",
      "deathYear": "1955",
      "portraitUrl": "https://upload.wikimedia.org/wikipedia/commons/e/e0/Yves_Tanguy.jpg",
      "portraitThumbnailUrl": "https://upload.wikimedia.org/wikipedia/commons/e/e0/Yves_Tanguy.jpg",
      "localPosition": { "x": 0.8, "y": -0.2, "z": -0.6 },
      "artworks": [
        {
          "id": "Q328581",
          "title": "Surreal Landscape",
          "year": "1927",
          "imageHighResUrl": "https://upload.wikimedia.org/wikipedia/en/2/23/Mama%2C_Papa_is_Wounded%21.jpg",
          "imageThumbnailUrl": "https://upload.wikimedia.org/wikipedia/en/2/23/Mama%2C_Papa_is_Wounded%21.jpg",
          "dimensions": { "width": 2000, "height": 2500 },
          "aspectRatio": 0.80,
          "description": "A quiet landscape featuring biomorphic shapes and a mysterious atmosphere."
        }
      ]
    },
    {
      "id": "Q234293",
      "name": "Leonora Carrington",
      "birthYear": "1917",
      "deathYear": "2011",
      "portraitUrl": "https://upload.wikimedia.org/wikipedia/commons/7/7b/Leonora_Carrington.jpg",
      "portraitThumbnailUrl": "https://upload.wikimedia.org/wikipedia/commons/7/7b/Leonora_Carrington.jpg",
      "localPosition": { "x": -0.8, "y": 0.6, "z": -0.2 },
      "artworks": [
        {
          "id": "Q4534",
          "title": "Portrait of Max Ernst",
          "year": "1939",
          "imageHighResUrl": "https://upload.wikimedia.org/wikipedia/en/b/b3/Leonora_Carrington_-_Portrait_of_Max_Ernst.jpg",
          "imageThumbnailUrl": "https://upload.wikimedia.org/wikipedia/en/b/b3/Leonora_Carrington_-_Portrait_of_Max_Ernst.jpg",
          "dimensions": { "width": 2000, "height": 2400 },
          "aspectRatio": 0.83,
          "description": "A mystical portrait incorporating esoteric symbols and animal familiars."
        }
      ]
    },
    {
      "id": "Q238289",
      "name": "Remedios Varo",
      "birthYear": "1908",
      "deathYear": "1963",
      "portraitUrl": "https://upload.wikimedia.org/wikipedia/commons/e/e9/Remedios_Varo.jpg",
      "portraitThumbnailUrl": "https://upload.wikimedia.org/wikipedia/commons/e/e9/Remedios_Varo.jpg",
      "localPosition": { "x": 0.3, "y": 0.7, "z": 0.8 },
      "artworks": [
        {
          "id": "Q33445",
          "title": "The Creation of the Birds",
          "year": "1957",
          "imageHighResUrl": "https://upload.wikimedia.org/wikipedia/en/9/9f/Remedios_Varo_-_Creation_of_the_Birds.jpg",
          "imageThumbnailUrl": "https://upload.wikimedia.org/wikipedia/en/9/9f/Remedios_Varo_-_Creation_of_the_Birds.jpg",
          "dimensions": { "width": 2500, "height": 2000 },
          "aspectRatio": 1.25,
          "description": "An alchemical scene depicting a figure crafting birds that come to life."
        }
      ]
    },
    {
      "id": "Q164670",
      "name": "Paul Delvaux",
      "birthYear": "1897",
      "deathYear": "1994",
      "portraitUrl": "https://upload.wikimedia.org/wikipedia/commons/5/5a/Paul_Delvaux.jpg",
      "portraitThumbnailUrl": "https://upload.wikimedia.org/wikipedia/commons/5/5a/Paul_Delvaux.jpg",
      "localPosition": { "x": 0.1, "y": -0.8, "z": -0.7 },
      "artworks": [
        {
          "id": "Q2243",
          "title": "The Sleeping Venus",
          "year": "1944",
          "imageHighResUrl": "https://upload.wikimedia.org/wikipedia/en/4/4b/Paul_Delvaux_-_The_Sleeping_Venus.jpg",
          "imageThumbnailUrl": "https://upload.wikimedia.org/wikipedia/en/4/4b/Paul_Delvaux_-_The_Sleeping_Venus.jpg",
          "dimensions": { "width": 3000, "height": 1800 },
          "aspectRatio": 1.67,
          "description": "A classical figure surrounded by statues and melancholic characters in a nocturnal city."
        }
      ]
    },
    {
      "id": "Q237996",
      "name": "Dorothea Tanning",
      "birthYear": "1910",
      "deathYear": "2012",
      "portraitUrl": "https://upload.wikimedia.org/wikipedia/commons/4/4a/Dorothea_Tanning.jpg",
      "portraitThumbnailUrl": "https://upload.wikimedia.org/wikipedia/commons/4/4a/Dorothea_Tanning.jpg",
      "localPosition": { "x": -0.7, "y": -0.6, "z": 0.4 },
      "artworks": [
        {
          "id": "Q234",
          "title": "Eine Kleine Nachtmusik",
          "year": "1943",
          "imageHighResUrl": "https://upload.wikimedia.org/wikipedia/en/7/77/Dorothea_Tanning_-_Eine_Kleine_Nachtmusik.jpg",
          "imageThumbnailUrl": "https://upload.wikimedia.org/wikipedia/en/7/77/Dorothea_Tanning_-_Eine_Kleine_Nachtmusik.jpg",
          "dimensions": { "width": 2400, "height": 3000 },
          "aspectRatio": 0.80,
          "description": "A dreamlike corridor featuring giant sunflowers and uncanny childhood figures."
        }
      ]
    },
    {
      "id": "Q165313",
      "name": "André Masson",
      "birthYear": "1896",
      "deathYear": "1987",
      "portraitUrl": "https://upload.wikimedia.org/wikipedia/commons/1/1b/Andre_Masson.jpg",
      "portraitThumbnailUrl": "https://upload.wikimedia.org/wikipedia/commons/1/1b/Andre_Masson.jpg",
      "localPosition": { "x": 0.7, "y": -0.1, "z": 0.9 },
      "artworks": [
        {
          "id": "Q4433",
          "title": "Abstract Fishes",
          "year": "1926",
          "imageHighResUrl": "https://upload.wikimedia.org/wikipedia/en/3/3d/Andre_Masson_-_Battle_of_Fishes.jpg",
          "imageThumbnailUrl": "https://upload.wikimedia.org/wikipedia/en/3/3d/Andre_Masson_-_Battle_of_Fishes.jpg",
          "dimensions": { "width": 3000, "height": 2000 },
          "aspectRatio": 1.50,
          "description": "An automatic painting utilizing sand and pigment to express intense themes."
        }
      ]
    }
  ]
}